[
    {
      "title": "EXORCIST BELIEVER",
      "poster": "image/exorcist.jpg",
      "garahhugatsaa": "2023.09.23",
      "torol": "DRAMA/HISTORY",
      "urgeljlehhugatsaa": "1 цаг 30мин"
    },
    {
      "title": "SAW X",
      "poster": "image/saw.jpeg",
      "garahhugatsaa": "2023.09.23",
      "torol": "DRAMA/ACTION",
      "urgeljlehhugatsaa": "2 цаг"
    },
    {
      "title": "THE PURGE",
      "poster": "image/thepurge.jpeg",
      "garahhugatsaa": "2023.11.30",
      "torol": "HORROR/ACTION",
      "urgeljlehhugatsaa": "2 цаг 15мин"
    }
  ]
  